dx_mcp_server/__init__.py
dx_mcp_server/__main__.py
dx_mcp_server/main.py
dx_mcp_server/server.py
dx_mcp_server/prompts/__init__.py
dx_mcp_server/prompts/scorecard_prompts.py
dx_mcp_server/tools/__init__.py
dx_mcp_server/tools/data_tools.py
dx_mcp_server/tools/entity_tools.py
dx_mcp_server/tools/scorecard_tools.py
dx_mcp_server/tools/team_tools.py
dx_mcp_server-1.3.0.dist-info/METADATA
dx_mcp_server-1.3.0.dist-info/WHEEL
dx_mcp_server-1.3.0.dist-info/entry_points.txt
dx_mcp_server-1.3.0.dist-info/licenses/LICENSE
dx_mcp_server-1.3.0.dist-info/RECORD
