Metadata-Version: 2.4
Name: dx-mcp-server
Version: 1.3.0
Summary: Use natural language to write and execute queries on your organizational data in DX Data Cloud
Project-URL: Homepage, https://github.com/get-dx/dx-mcp-server
Author-email: Zak Hijaouy <zak.hijaouy@getdx.com>
License: MIT
License-File: LICENSE
Requires-Python: >=3.10
Requires-Dist: fastmcp>=2.14.3
Requires-Dist: psycopg[binary]>=3.0.0
Requires-Dist: requests>=2.32.0
